lvis/__init__.py
lvis/colormap.py
lvis/eval.py
lvis/lvis.py
lvis/results.py
lvis/vis.py
lvis-0.5.2.dist-info/LICENSE
lvis-0.5.2.dist-info/METADATA
lvis-0.5.2.dist-info/WHEEL
lvis-0.5.2.dist-info/top_level.txt
lvis-0.5.2.dist-info/RECORD
