Metadata-Version: 2.1
Name: lvis
Version: 0.5.2
Summary: Python API for LVIS dataset.
Home-page: UNKNOWN
Author: Agrim Gupta
License: UNKNOWN
Platform: UNKNOWN
Requires-Dist: cycler (==0.10.0)
Requires-Dist: Cython (==0.29.12)
Requires-Dist: kiwisolver (==1.1.0)
Requires-Dist: matplotlib (==3.1.1)
Requires-Dist: numpy (==1.18.2)
Requires-Dist: opencv-python (==4.1.0.25)
Requires-Dist: pyparsing (==2.4.0)
Requires-Dist: python-dateutil (==2.8.0)
Requires-Dist: six (==1.12.0)
